[
    {
        "ai": false,
        "car_number": "215",
        "cust_id": 606742,
        "display_name": "Raul Onta\u00f1on",
        "flags": 3,
        "group_id": -299638,
        "helmet": {
            "color1": "1458a6",
            "color2": "673e97",
            "color3": "000000",
            "face_type": 0,
            "helmet_type": 0,
            "pattern": 57
        },
        "incident": false,
        "lap_events": [
            "invalid",
            "pitted"
        ],
        "lap_number": 54,
        "lap_time": 3021798,
        "license_level": 19,
        "name": "Ingersoll Rand Enosis eSports #215",
        "personal_best_lap": false,
        "session_start_time": null,
        "session_time": 134242767,
        "team_fastest_lap": false
    },
    {
        "ai": false,
        "car_number": "215",
        "cust_id": 606742,
        "display_name": "Raul Onta\u00f1on",
        "flags": 0,
        "group_id": -299638,
        "helmet": {
            "color1": "1458a6",
            "color2": "673e97",
            "color3": "000000",
            "face_type": 0,
            "helmet_type": 0,
            "pattern": 57
        },
        "incident": false,
        "lap_events": [],
        "lap_number": 55,
        "lap_time": 2381897,
        "license_level": 19,
        "name": "Ingersoll Rand Enosis eSports #215",
        "personal_best_lap": false,
        "session_start_time": null,
        "session_time": 136624664,
        "team_fastest_lap": false
    },
    {
        "ai": false,
        "car_number": "215",
        "cust_id": 606742,
        "display_name": "Raul Onta\u00f1on",
        "flags": 0,
        "group_id": -299638,
        "helmet": {
            "color1": "1458a6",
            "color2": "673e97",
            "color3": "000000",
            "face_type": 0,
            "helmet_type": 0,
            "pattern": 57
        },
        "incident": false,
        "lap_events": [],
        "lap_number": 56,
        "lap_time": 2390551,
        "license_level": 19,
        "name": "Ingersoll Rand Enosis eSports #215",
        "personal_best_lap": false,
        "session_start_time": null,
        "session_time": 139015215,
        "team_fastest_lap": false
    },
    {
        "ai": false,
        "car_number": "215",
        "cust_id": 606742,
        "display_name": "Raul Onta\u00f1on",
        "flags": 0,
        "group_id": -299638,
        "helmet": {
            "color1": "1458a6",
            "color2": "673e97",
            "color3": "000000",
            "face_type": 0,
            "helmet_type": 0,
            "pattern": 57
        },
        "incident": false,
        "lap_events": [],
        "lap_number": 57,
        "lap_time": 2379417,
        "license_level": 19,
        "name": "Ingersoll Rand Enosis eSports #215",
        "personal_best_lap": false,
        "session_start_time": null,
        "session_time": 141394632,
        "team_fastest_lap": false
    },
    {
        "ai": false,
        "car_number": "215",
        "cust_id": 606742,
        "display_name": "Raul Onta\u00f1on",
        "flags": 0,
        "group_id": -299638,
        "helmet": {
            "color1": "1458a6",
            "color2": "673e97",
            "color3": "000000",
            "face_type": 0,
            "helmet_type": 0,
            "pattern": 57
        },
        "incident": false,
        "lap_events": [],
        "lap_number": 58,
        "lap_time": 2368819,
        "license_level": 19,
        "name": "Ingersoll Rand Enosis eSports #215",
        "personal_best_lap": false,
        "session_start_time": null,
        "session_time": 143763451,
        "team_fastest_lap": false
    },
    {
        "ai": false,
        "car_number": "215",
        "cust_id": 606742,
        "display_name": "Raul Onta\u00f1on",
        "flags": 0,
        "group_id": -299638,
        "helmet": {
            "color1": "1458a6",
            "color2": "673e97",
            "color3": "000000",
            "face_type": 0,
            "helmet_type": 0,
            "pattern": 57
        },
        "incident": false,
        "lap_events": [],
        "lap_number": 59,
        "lap_time": 2363434,
        "license_level": 19,
        "name": "Ingersoll Rand Enosis eSports #215",
        "personal_best_lap": false,
        "session_start_time": null,
        "session_time": 146126885,
        "team_fastest_lap": false
    },
    {
        "ai": false,
        "car_number": "215",
        "cust_id": 606742,
        "display_name": "Raul Onta\u00f1on",
        "flags": 0,
        "group_id": -299638,
        "helmet": {
            "color1": "1458a6",
            "color2": "673e97",
            "color3": "000000",
            "face_type": 0,
            "helmet_type": 0,
            "pattern": 57
        },
        "incident": false,
        "lap_events": [],
        "lap_number": 60,
        "lap_time": 2364578,
        "license_level": 19,
        "name": "Ingersoll Rand Enosis eSports #215",
        "personal_best_lap": false,
        "session_start_time": null,
        "session_time": 148491463,
        "team_fastest_lap": false
    },
    {
        "ai": false,
        "car_number": "215",
        "cust_id": 606742,
        "display_name": "Raul Onta\u00f1on",
        "flags": 0,
        "group_id": -299638,
        "helmet": {
            "color1": "1458a6",
            "color2": "673e97",
            "color3": "000000",
            "face_type": 0,
            "helmet_type": 0,
            "pattern": 57
        },
        "incident": false,
        "lap_events": [],
        "lap_number": 61,
        "lap_time": 2361217,
        "license_level": 19,
        "name": "Ingersoll Rand Enosis eSports #215",
        "personal_best_lap": false,
        "session_start_time": null,
        "session_time": 150852680,
        "team_fastest_lap": false
    },
    {
        "ai": false,
        "car_number": "215",
        "cust_id": 606742,
        "display_name": "Raul Onta\u00f1on",
        "flags": 0,
        "group_id": -299638,
        "helmet": {
            "color1": "1458a6",
            "color2": "673e97",
            "color3": "000000",
            "face_type": 0,
            "helmet_type": 0,
            "pattern": 57
        },
        "incident": false,
        "lap_events": [],
        "lap_number": 62,
        "lap_time": 2359517,
        "license_level": 19,
        "name": "Ingersoll Rand Enosis eSports #215",
        "personal_best_lap": false,
        "session_start_time": null,
        "session_time": 153212197,
        "team_fastest_lap": false
    },
    {
        "ai": false,
        "car_number": "215",
        "cust_id": 606742,
        "display_name": "Raul Onta\u00f1on",
        "flags": 0,
        "group_id": -299638,
        "helmet": {
            "color1": "1458a6",
            "color2": "673e97",
            "color3": "000000",
            "face_type": 0,
            "helmet_type": 0,
            "pattern": 57
        },
        "incident": false,
        "lap_events": [],
        "lap_number": 63,
        "lap_time": 2364063,
        "license_level": 19,
        "name": "Ingersoll Rand Enosis eSports #215",
        "personal_best_lap": false,
        "session_start_time": null,
        "session_time": 155576260,
        "team_fastest_lap": false
    },
    {
        "ai": false,
        "car_number": "215",
        "cust_id": 606742,
        "display_name": "Raul Onta\u00f1on",
        "flags": 0,
        "group_id": -299638,
        "helmet": {
            "color1": "1458a6",
            "color2": "673e97",
            "color3": "000000",
            "face_type": 0,
            "helmet_type": 0,
            "pattern": 57
        },
        "incident": false,
        "lap_events": [],
        "lap_number": 64,
        "lap_time": 2357974,
        "license_level": 19,
        "name": "Ingersoll Rand Enosis eSports #215",
        "personal_best_lap": false,
        "session_start_time": null,
        "session_time": 157934234,
        "team_fastest_lap": false
    },
    {
        "ai": false,
        "car_number": "215",
        "cust_id": 606742,
        "display_name": "Raul Onta\u00f1on",
        "flags": 0,
        "group_id": -299638,
        "helmet": {
            "color1": "1458a6",
            "color2": "673e97",
            "color3": "000000",
            "face_type": 0,
            "helmet_type": 0,
            "pattern": 57
        },
        "incident": false,
        "lap_events": [],
        "lap_number": 65,
        "lap_time": 2354942,
        "license_level": 19,
        "name": "Ingersoll Rand Enosis eSports #215",
        "personal_best_lap": false,
        "session_start_time": null,
        "session_time": 160289176,
        "team_fastest_lap": false
    },
    {
        "ai": false,
        "car_number": "215",
        "cust_id": 606742,
        "display_name": "Raul Onta\u00f1on",
        "flags": 2,
        "group_id": -299638,
        "helmet": {
            "color1": "1458a6",
            "color2": "673e97",
            "color3": "000000",
            "face_type": 0,
            "helmet_type": 0,
            "pattern": 57
        },
        "incident": false,
        "lap_events": [
            "pitted"
        ],
        "lap_number": 66,
        "lap_time": 2406812,
        "license_level": 19,
        "name": "Ingersoll Rand Enosis eSports #215",
        "personal_best_lap": false,
        "session_start_time": null,
        "session_time": 162695988,
        "team_fastest_lap": false
    },
    {
        "ai": false,
        "car_number": "215",
        "cust_id": 606742,
        "display_name": "Raul Onta\u00f1on",
        "flags": 2,
        "group_id": -299638,
        "helmet": {
            "color1": "1458a6",
            "color2": "673e97",
            "color3": "000000",
            "face_type": 0,
            "helmet_type": 0,
            "pattern": 57
        },
        "incident": false,
        "lap_events": [
            "pitted"
        ],
        "lap_number": 67,
        "lap_time": 2951812,
        "license_level": 19,
        "name": "Ingersoll Rand Enosis eSports #215",
        "personal_best_lap": false,
        "session_start_time": null,
        "session_time": 165647800,
        "team_fastest_lap": false
    },
    {
        "ai": false,
        "car_number": "215",
        "cust_id": 606742,
        "display_name": "Raul Onta\u00f1on",
        "flags": 0,
        "group_id": -299638,
        "helmet": {
            "color1": "1458a6",
            "color2": "673e97",
            "color3": "000000",
            "face_type": 0,
            "helmet_type": 0,
            "pattern": 57
        },
        "incident": false,
        "lap_events": [],
        "lap_number": 68,
        "lap_time": 2361271,
        "license_level": 19,
        "name": "Ingersoll Rand Enosis eSports #215",
        "personal_best_lap": false,
        "session_start_time": null,
        "session_time": 168009071,
        "team_fastest_lap": false
    },
    {
        "ai": false,
        "car_number": "215",
        "cust_id": 606742,
        "display_name": "Raul Onta\u00f1on",
        "flags": 0,
        "group_id": -299638,
        "helmet": {
            "color1": "1458a6",
            "color2": "673e97",
            "color3": "000000",
            "face_type": 0,
            "helmet_type": 0,
            "pattern": 57
        },
        "incident": false,
        "lap_events": [],
        "lap_number": 69,
        "lap_time": 2361700,
        "license_level": 19,
        "name": "Ingersoll Rand Enosis eSports #215",
        "personal_best_lap": false,
        "session_start_time": null,
        "session_time": 170370771,
        "team_fastest_lap": false
    },
    {
        "ai": false,
        "car_number": "215",
        "cust_id": 606742,
        "display_name": "Raul Onta\u00f1on",
        "flags": 0,
        "group_id": -299638,
        "helmet": {
            "color1": "1458a6",
            "color2": "673e97",
            "color3": "000000",
            "face_type": 0,
            "helmet_type": 0,
            "pattern": 57
        },
        "incident": false,
        "lap_events": [],
        "lap_number": 70,
        "lap_time": 2369503,
        "license_level": 19,
        "name": "Ingersoll Rand Enosis eSports #215",
        "personal_best_lap": false,
        "session_start_time": null,
        "session_time": 172740274,
        "team_fastest_lap": false
    },
    {
        "ai": false,
        "car_number": "215",
        "cust_id": 606742,
        "display_name": "Raul Onta\u00f1on",
        "flags": 0,
        "group_id": -299638,
        "helmet": {
            "color1": "1458a6",
            "color2": "673e97",
            "color3": "000000",
            "face_type": 0,
            "helmet_type": 0,
            "pattern": 57
        },
        "incident": false,
        "lap_events": [],
        "lap_number": 71,
        "lap_time": 2359649,
        "license_level": 19,
        "name": "Ingersoll Rand Enosis eSports #215",
        "personal_best_lap": false,
        "session_start_time": null,
        "session_time": 175099923,
        "team_fastest_lap": false
    },
    {
        "ai": false,
        "car_number": "215",
        "cust_id": 606742,
        "display_name": "Raul Onta\u00f1on",
        "flags": 0,
        "group_id": -299638,
        "helmet": {
            "color1": "1458a6",
            "color2": "673e97",
            "color3": "000000",
            "face_type": 0,
            "helmet_type": 0,
            "pattern": 57
        },
        "incident": false,
        "lap_events": [],
        "lap_number": 72,
        "lap_time": 2388821,
        "license_level": 19,
        "name": "Ingersoll Rand Enosis eSports #215",
        "personal_best_lap": false,
        "session_start_time": null,
        "session_time": 177488744,
        "team_fastest_lap": false
    },
    {
        "ai": false,
        "car_number": "215",
        "cust_id": 606742,
        "display_name": "Raul Onta\u00f1on",
        "flags": 0,
        "group_id": -299638,
        "helmet": {
            "color1": "1458a6",
            "color2": "673e97",
            "color3": "000000",
            "face_type": 0,
            "helmet_type": 0,
            "pattern": 57
        },
        "incident": false,
        "lap_events": [],
        "lap_number": 73,
        "lap_time": 2358110,
        "license_level": 19,
        "name": "Ingersoll Rand Enosis eSports #215",
        "personal_best_lap": false,
        "session_start_time": null,
        "session_time": 179846854,
        "team_fastest_lap": false
    },
    {
        "ai": false,
        "car_number": "215",
        "cust_id": 606742,
        "display_name": "Raul Onta\u00f1on",
        "flags": 0,
        "group_id": -299638,
        "helmet": {
            "color1": "1458a6",
            "color2": "673e97",
            "color3": "000000",
            "face_type": 0,
            "helmet_type": 0,
            "pattern": 57
        },
        "incident": false,
        "lap_events": [],
        "lap_number": 74,
        "lap_time": 2368170,
        "license_level": 19,
        "name": "Ingersoll Rand Enosis eSports #215",
        "personal_best_lap": false,
        "session_start_time": null,
        "session_time": 182215024,
        "team_fastest_lap": false
    },
    {
        "ai": false,
        "car_number": "215",
        "cust_id": 606742,
        "display_name": "Raul Onta\u00f1on",
        "flags": 0,
        "group_id": -299638,
        "helmet": {
            "color1": "1458a6",
            "color2": "673e97",
            "color3": "000000",
            "face_type": 0,
            "helmet_type": 0,
            "pattern": 57
        },
        "incident": false,
        "lap_events": [],
        "lap_number": 75,
        "lap_time": 2357162,
        "license_level": 19,
        "name": "Ingersoll Rand Enosis eSports #215",
        "personal_best_lap": false,
        "session_start_time": null,
        "session_time": 184572186,
        "team_fastest_lap": false
    },
    {
        "ai": false,
        "car_number": "215",
        "cust_id": 606742,
        "display_name": "Raul Onta\u00f1on",
        "flags": 0,
        "group_id": -299638,
        "helmet": {
            "color1": "1458a6",
            "color2": "673e97",
            "color3": "000000",
            "face_type": 0,
            "helmet_type": 0,
            "pattern": 57
        },
        "incident": false,
        "lap_events": [],
        "lap_number": 76,
        "lap_time": 2361012,
        "license_level": 19,
        "name": "Ingersoll Rand Enosis eSports #215",
        "personal_best_lap": false,
        "session_start_time": null,
        "session_time": 186933198,
        "team_fastest_lap": false
    },
    {
        "ai": false,
        "car_number": "215",
        "cust_id": 606742,
        "display_name": "Raul Onta\u00f1on",
        "flags": 0,
        "group_id": -299638,
        "helmet": {
            "color1": "1458a6",
            "color2": "673e97",
            "color3": "000000",
            "face_type": 0,
            "helmet_type": 0,
            "pattern": 57
        },
        "incident": false,
        "lap_events": [],
        "lap_number": 77,
        "lap_time": 2361013,
        "license_level": 19,
        "name": "Ingersoll Rand Enosis eSports #215",
        "personal_best_lap": false,
        "session_start_time": null,
        "session_time": 189294211,
        "team_fastest_lap": false
    },
    {
        "ai": false,
        "car_number": "215",
        "cust_id": 606742,
        "display_name": "Raul Onta\u00f1on",
        "flags": 0,
        "group_id": -299638,
        "helmet": {
            "color1": "1458a6",
            "color2": "673e97",
            "color3": "000000",
            "face_type": 0,
            "helmet_type": 0,
            "pattern": 57
        },
        "incident": false,
        "lap_events": [],
        "lap_number": 78,
        "lap_time": 2368856,
        "license_level": 19,
        "name": "Ingersoll Rand Enosis eSports #215",
        "personal_best_lap": false,
        "session_start_time": null,
        "session_time": 191663067,
        "team_fastest_lap": false
    },
    {
        "ai": false,
        "car_number": "215",
        "cust_id": 606742,
        "display_name": "Raul Onta\u00f1on",
        "flags": 2,
        "group_id": -299638,
        "helmet": {
            "color1": "1458a6",
            "color2": "673e97",
            "color3": "000000",
            "face_type": 0,
            "helmet_type": 0,
            "pattern": 57
        },
        "incident": false,
        "lap_events": [
            "pitted"
        ],
        "lap_number": 79,
        "lap_time": 2406615,
        "license_level": 19,
        "name": "Ingersoll Rand Enosis eSports #215",
        "personal_best_lap": false,
        "session_start_time": null,
        "session_time": 194069682,
        "team_fastest_lap": false
    },
    {
        "ai": false,
        "car_number": "215",
        "cust_id": 606742,
        "display_name": "Raul Onta\u00f1on",
        "flags": 2,
        "group_id": -299638,
        "helmet": {
            "color1": "1458a6",
            "color2": "673e97",
            "color3": "000000",
            "face_type": 0,
            "helmet_type": 0,
            "pattern": 57
        },
        "incident": false,
        "lap_events": [
            "pitted"
        ],
        "lap_number": 80,
        "lap_time": 2944645,
        "license_level": 19,
        "name": "Ingersoll Rand Enosis eSports #215",
        "personal_best_lap": false,
        "session_start_time": null,
        "session_time": 197014327,
        "team_fastest_lap": false
    },
    {
        "ai": false,
        "car_number": "215",
        "cust_id": 606742,
        "display_name": "Raul Onta\u00f1on",
        "flags": 0,
        "group_id": -299638,
        "helmet": {
            "color1": "1458a6",
            "color2": "673e97",
            "color3": "000000",
            "face_type": 0,
            "helmet_type": 0,
            "pattern": 57
        },
        "incident": false,
        "lap_events": [],
        "lap_number": 81,
        "lap_time": 2368182,
        "license_level": 19,
        "name": "Ingersoll Rand Enosis eSports #215",
        "personal_best_lap": false,
        "session_start_time": null,
        "session_time": 199382509,
        "team_fastest_lap": false
    },
    {
        "ai": false,
        "car_number": "215",
        "cust_id": 606742,
        "display_name": "Raul Onta\u00f1on",
        "flags": 0,
        "group_id": -299638,
        "helmet": {
            "color1": "1458a6",
            "color2": "673e97",
            "color3": "000000",
            "face_type": 0,
            "helmet_type": 0,
            "pattern": 57
        },
        "incident": false,
        "lap_events": [],
        "lap_number": 82,
        "lap_time": 2368490,
        "license_level": 19,
        "name": "Ingersoll Rand Enosis eSports #215",
        "personal_best_lap": false,
        "session_start_time": null,
        "session_time": 201750999,
        "team_fastest_lap": false
    },
    {
        "ai": false,
        "car_number": "215",
        "cust_id": 606742,
        "display_name": "Raul Onta\u00f1on",
        "flags": 0,
        "group_id": -299638,
        "helmet": {
            "color1": "1458a6",
            "color2": "673e97",
            "color3": "000000",
            "face_type": 0,
            "helmet_type": 0,
            "pattern": 57
        },
        "incident": false,
        "lap_events": [],
        "lap_number": 83,
        "lap_time": 2355598,
        "license_level": 19,
        "name": "Ingersoll Rand Enosis eSports #215",
        "personal_best_lap": false,
        "session_start_time": null,
        "session_time": 204106597,
        "team_fastest_lap": false
    },
    {
        "ai": false,
        "car_number": "215",
        "cust_id": 606742,
        "display_name": "Raul Onta\u00f1on",
        "flags": 0,
        "group_id": -299638,
        "helmet": {
            "color1": "1458a6",
            "color2": "673e97",
            "color3": "000000",
            "face_type": 0,
            "helmet_type": 0,
            "pattern": 57
        },
        "incident": false,
        "lap_events": [],
        "lap_number": 84,
        "lap_time": 2356739,
        "license_level": 19,
        "name": "Ingersoll Rand Enosis eSports #215",
        "personal_best_lap": false,
        "session_start_time": null,
        "session_time": 206463336,
        "team_fastest_lap": false
    },
    {
        "ai": false,
        "car_number": "215",
        "cust_id": 606742,
        "display_name": "Raul Onta\u00f1on",
        "flags": 0,
        "group_id": -299638,
        "helmet": {
            "color1": "1458a6",
            "color2": "673e97",
            "color3": "000000",
            "face_type": 0,
            "helmet_type": 0,
            "pattern": 57
        },
        "incident": false,
        "lap_events": [],
        "lap_number": 85,
        "lap_time": 2351972,
        "license_level": 19,
        "name": "Ingersoll Rand Enosis eSports #215",
        "personal_best_lap": false,
        "session_start_time": null,
        "session_time": 208815308,
        "team_fastest_lap": false
    },
    {
        "ai": false,
        "car_number": "215",
        "cust_id": 606742,
        "display_name": "Raul Onta\u00f1on",
        "flags": 0,
        "group_id": -299638,
        "helmet": {
            "color1": "1458a6",
            "color2": "673e97",
            "color3": "000000",
            "face_type": 0,
            "helmet_type": 0,
            "pattern": 57
        },
        "incident": false,
        "lap_events": [],
        "lap_number": 86,
        "lap_time": 2346137,
        "license_level": 19,
        "name": "Ingersoll Rand Enosis eSports #215",
        "personal_best_lap": false,
        "session_start_time": null,
        "session_time": 211161445,
        "team_fastest_lap": false
    },
    {
        "ai": false,
        "car_number": "215",
        "cust_id": 606742,
        "display_name": "Raul Onta\u00f1on",
        "flags": 0,
        "group_id": -299638,
        "helmet": {
            "color1": "1458a6",
            "color2": "673e97",
            "color3": "000000",
            "face_type": 0,
            "helmet_type": 0,
            "pattern": 57
        },
        "incident": false,
        "lap_events": [],
        "lap_number": 87,
        "lap_time": 2348202,
        "license_level": 19,
        "name": "Ingersoll Rand Enosis eSports #215",
        "personal_best_lap": false,
        "session_start_time": null,
        "session_time": 213509647,
        "team_fastest_lap": false
    },
    {
        "ai": false,
        "car_number": "215",
        "cust_id": 606742,
        "display_name": "Raul Onta\u00f1on",
        "flags": 0,
        "group_id": -299638,
        "helmet": {
            "color1": "1458a6",
            "color2": "673e97",
            "color3": "000000",
            "face_type": 0,
            "helmet_type": 0,
            "pattern": 57
        },
        "incident": false,
        "lap_events": [],
        "lap_number": 88,
        "lap_time": 2350681,
        "license_level": 19,
        "name": "Ingersoll Rand Enosis eSports #215",
        "personal_best_lap": false,
        "session_start_time": null,
        "session_time": 215860328,
        "team_fastest_lap": false
    },
    {
        "ai": false,
        "car_number": "215",
        "cust_id": 606742,
        "display_name": "Raul Onta\u00f1on",
        "flags": 0,
        "group_id": -299638,
        "helmet": {
            "color1": "1458a6",
            "color2": "673e97",
            "color3": "000000",
            "face_type": 0,
            "helmet_type": 0,
            "pattern": 57
        },
        "incident": false,
        "lap_events": [],
        "lap_number": 89,
        "lap_time": 2344288,
        "license_level": 19,
        "name": "Ingersoll Rand Enosis eSports #215",
        "personal_best_lap": true,
        "session_start_time": null,
        "session_time": 218204616,
        "team_fastest_lap": true
    },
    {
        "ai": false,
        "car_number": "215",
        "cust_id": 606742,
        "display_name": "Raul Onta\u00f1on",
        "flags": 16384,
        "group_id": -299638,
        "helmet": {
            "color1": "1458a6",
            "color2": "673e97",
            "color3": "000000",
            "face_type": 0,
            "helmet_type": 0,
            "pattern": 57
        },
        "incident": false,
        "lap_events": [],
        "lap_number": 90,
        "lap_time": 2361959,
        "license_level": 19,
        "name": "Ingersoll Rand Enosis eSports #215",
        "personal_best_lap": false,
        "session_start_time": null,
        "session_time": 220566575,
        "team_fastest_lap": false
    }
]