[
    {
        "ai": false,
        "car_number": "211",
        "cust_id": 676270,
        "display_name": "Cassio Medeiros",
        "flags": 3,
        "group_id": -134184,
        "helmet": {
            "color1": "ff0000",
            "color2": "000000",
            "color3": "ffffff",
            "face_type": 0,
            "helmet_type": 0,
            "pattern": 1
        },
        "incident": false,
        "lap_events": [
            "invalid",
            "pitted"
        ],
        "lap_number": 40,
        "lap_time": 3059141,
        "license_level": 18,
        "name": "GROW RACING TEAM RED",
        "personal_best_lap": false,
        "session_start_time": null,
        "session_time": 100439415,
        "team_fastest_lap": false
    },
    {
        "ai": false,
        "car_number": "211",
        "cust_id": 676270,
        "display_name": "Cassio Medeiros",
        "flags": 0,
        "group_id": -134184,
        "helmet": {
            "color1": "ff0000",
            "color2": "000000",
            "color3": "ffffff",
            "face_type": 0,
            "helmet_type": 0,
            "pattern": 1
        },
        "incident": false,
        "lap_events": [],
        "lap_number": 41,
        "lap_time": 2398989,
        "license_level": 18,
        "name": "GROW RACING TEAM RED",
        "personal_best_lap": false,
        "session_start_time": null,
        "session_time": 102838404,
        "team_fastest_lap": false
    },
    {
        "ai": false,
        "car_number": "211",
        "cust_id": 676270,
        "display_name": "Cassio Medeiros",
        "flags": 0,
        "group_id": -134184,
        "helmet": {
            "color1": "ff0000",
            "color2": "000000",
            "color3": "ffffff",
            "face_type": 0,
            "helmet_type": 0,
            "pattern": 1
        },
        "incident": false,
        "lap_events": [],
        "lap_number": 42,
        "lap_time": 2403097,
        "license_level": 18,
        "name": "GROW RACING TEAM RED",
        "personal_best_lap": false,
        "session_start_time": null,
        "session_time": 105241501,
        "team_fastest_lap": false
    },
    {
        "ai": false,
        "car_number": "211",
        "cust_id": 676270,
        "display_name": "Cassio Medeiros",
        "flags": 0,
        "group_id": -134184,
        "helmet": {
            "color1": "ff0000",
            "color2": "000000",
            "color3": "ffffff",
            "face_type": 0,
            "helmet_type": 0,
            "pattern": 1
        },
        "incident": false,
        "lap_events": [],
        "lap_number": 43,
        "lap_time": 2386987,
        "license_level": 18,
        "name": "GROW RACING TEAM RED",
        "personal_best_lap": false,
        "session_start_time": null,
        "session_time": 107628488,
        "team_fastest_lap": false
    },
    {
        "ai": false,
        "car_number": "211",
        "cust_id": 676270,
        "display_name": "Cassio Medeiros",
        "flags": 0,
        "group_id": -134184,
        "helmet": {
            "color1": "ff0000",
            "color2": "000000",
            "color3": "ffffff",
            "face_type": 0,
            "helmet_type": 0,
            "pattern": 1
        },
        "incident": false,
        "lap_events": [],
        "lap_number": 44,
        "lap_time": 2407208,
        "license_level": 18,
        "name": "GROW RACING TEAM RED",
        "personal_best_lap": false,
        "session_start_time": null,
        "session_time": 110035696,
        "team_fastest_lap": false
    },
    {
        "ai": false,
        "car_number": "211",
        "cust_id": 676270,
        "display_name": "Cassio Medeiros",
        "flags": 0,
        "group_id": -134184,
        "helmet": {
            "color1": "ff0000",
            "color2": "000000",
            "color3": "ffffff",
            "face_type": 0,
            "helmet_type": 0,
            "pattern": 1
        },
        "incident": false,
        "lap_events": [],
        "lap_number": 45,
        "lap_time": 2398380,
        "license_level": 18,
        "name": "GROW RACING TEAM RED",
        "personal_best_lap": false,
        "session_start_time": null,
        "session_time": 112434076,
        "team_fastest_lap": false
    },
    {
        "ai": false,
        "car_number": "211",
        "cust_id": 676270,
        "display_name": "Cassio Medeiros",
        "flags": 0,
        "group_id": -134184,
        "helmet": {
            "color1": "ff0000",
            "color2": "000000",
            "color3": "ffffff",
            "face_type": 0,
            "helmet_type": 0,
            "pattern": 1
        },
        "incident": false,
        "lap_events": [],
        "lap_number": 46,
        "lap_time": 2389099,
        "license_level": 18,
        "name": "GROW RACING TEAM RED",
        "personal_best_lap": false,
        "session_start_time": null,
        "session_time": 114823175,
        "team_fastest_lap": false
    },
    {
        "ai": false,
        "car_number": "211",
        "cust_id": 676270,
        "display_name": "Cassio Medeiros",
        "flags": 0,
        "group_id": -134184,
        "helmet": {
            "color1": "ff0000",
            "color2": "000000",
            "color3": "ffffff",
            "face_type": 0,
            "helmet_type": 0,
            "pattern": 1
        },
        "incident": false,
        "lap_events": [],
        "lap_number": 47,
        "lap_time": 2383735,
        "license_level": 18,
        "name": "GROW RACING TEAM RED",
        "personal_best_lap": false,
        "session_start_time": null,
        "session_time": 117206910,
        "team_fastest_lap": false
    },
    {
        "ai": false,
        "car_number": "211",
        "cust_id": 676270,
        "display_name": "Cassio Medeiros",
        "flags": 0,
        "group_id": -134184,
        "helmet": {
            "color1": "ff0000",
            "color2": "000000",
            "color3": "ffffff",
            "face_type": 0,
            "helmet_type": 0,
            "pattern": 1
        },
        "incident": false,
        "lap_events": [],
        "lap_number": 48,
        "lap_time": 2396429,
        "license_level": 18,
        "name": "GROW RACING TEAM RED",
        "personal_best_lap": false,
        "session_start_time": null,
        "session_time": 119603339,
        "team_fastest_lap": false
    },
    {
        "ai": false,
        "car_number": "211",
        "cust_id": 676270,
        "display_name": "Cassio Medeiros",
        "flags": 0,
        "group_id": -134184,
        "helmet": {
            "color1": "ff0000",
            "color2": "000000",
            "color3": "ffffff",
            "face_type": 0,
            "helmet_type": 0,
            "pattern": 1
        },
        "incident": false,
        "lap_events": [],
        "lap_number": 49,
        "lap_time": 2381569,
        "license_level": 18,
        "name": "GROW RACING TEAM RED",
        "personal_best_lap": false,
        "session_start_time": null,
        "session_time": 121984908,
        "team_fastest_lap": false
    },
    {
        "ai": false,
        "car_number": "211",
        "cust_id": 676270,
        "display_name": "Cassio Medeiros",
        "flags": 0,
        "group_id": -134184,
        "helmet": {
            "color1": "ff0000",
            "color2": "000000",
            "color3": "ffffff",
            "face_type": 0,
            "helmet_type": 0,
            "pattern": 1
        },
        "incident": false,
        "lap_events": [],
        "lap_number": 50,
        "lap_time": 2388420,
        "license_level": 18,
        "name": "GROW RACING TEAM RED",
        "personal_best_lap": false,
        "session_start_time": null,
        "session_time": 124373328,
        "team_fastest_lap": false
    },
    {
        "ai": false,
        "car_number": "211",
        "cust_id": 676270,
        "display_name": "Cassio Medeiros",
        "flags": 0,
        "group_id": -134184,
        "helmet": {
            "color1": "ff0000",
            "color2": "000000",
            "color3": "ffffff",
            "face_type": 0,
            "helmet_type": 0,
            "pattern": 1
        },
        "incident": false,
        "lap_events": [],
        "lap_number": 51,
        "lap_time": 2397269,
        "license_level": 18,
        "name": "GROW RACING TEAM RED",
        "personal_best_lap": false,
        "session_start_time": null,
        "session_time": 126770597,
        "team_fastest_lap": false
    },
    {
        "ai": false,
        "car_number": "211",
        "cust_id": 676270,
        "display_name": "Cassio Medeiros",
        "flags": 2,
        "group_id": -134184,
        "helmet": {
            "color1": "ff0000",
            "color2": "000000",
            "color3": "ffffff",
            "face_type": 0,
            "helmet_type": 0,
            "pattern": 1
        },
        "incident": false,
        "lap_events": [
            "pitted"
        ],
        "lap_number": 52,
        "lap_time": 2433432,
        "license_level": 18,
        "name": "GROW RACING TEAM RED",
        "personal_best_lap": false,
        "session_start_time": null,
        "session_time": 129204029,
        "team_fastest_lap": false
    },
    {
        "ai": false,
        "car_number": "211",
        "cust_id": 676270,
        "display_name": "Cassio Medeiros",
        "flags": 2,
        "group_id": -134184,
        "helmet": {
            "color1": "ff0000",
            "color2": "000000",
            "color3": "ffffff",
            "face_type": 0,
            "helmet_type": 0,
            "pattern": 1
        },
        "incident": false,
        "lap_events": [
            "pitted"
        ],
        "lap_number": 53,
        "lap_time": 3023893,
        "license_level": 18,
        "name": "GROW RACING TEAM RED",
        "personal_best_lap": false,
        "session_start_time": null,
        "session_time": 132227922,
        "team_fastest_lap": false
    },
    {
        "ai": false,
        "car_number": "211",
        "cust_id": 676270,
        "display_name": "Cassio Medeiros",
        "flags": 0,
        "group_id": -134184,
        "helmet": {
            "color1": "ff0000",
            "color2": "000000",
            "color3": "ffffff",
            "face_type": 0,
            "helmet_type": 0,
            "pattern": 1
        },
        "incident": false,
        "lap_events": [],
        "lap_number": 54,
        "lap_time": 2405778,
        "license_level": 18,
        "name": "GROW RACING TEAM RED",
        "personal_best_lap": false,
        "session_start_time": null,
        "session_time": 134633700,
        "team_fastest_lap": false
    },
    {
        "ai": false,
        "car_number": "211",
        "cust_id": 676270,
        "display_name": "Cassio Medeiros",
        "flags": 0,
        "group_id": -134184,
        "helmet": {
            "color1": "ff0000",
            "color2": "000000",
            "color3": "ffffff",
            "face_type": 0,
            "helmet_type": 0,
            "pattern": 1
        },
        "incident": false,
        "lap_events": [],
        "lap_number": 55,
        "lap_time": 2392279,
        "license_level": 18,
        "name": "GROW RACING TEAM RED",
        "personal_best_lap": false,
        "session_start_time": null,
        "session_time": 137025979,
        "team_fastest_lap": false
    },
    {
        "ai": false,
        "car_number": "211",
        "cust_id": 676270,
        "display_name": "Cassio Medeiros",
        "flags": 0,
        "group_id": -134184,
        "helmet": {
            "color1": "ff0000",
            "color2": "000000",
            "color3": "ffffff",
            "face_type": 0,
            "helmet_type": 0,
            "pattern": 1
        },
        "incident": false,
        "lap_events": [],
        "lap_number": 56,
        "lap_time": 2393148,
        "license_level": 18,
        "name": "GROW RACING TEAM RED",
        "personal_best_lap": false,
        "session_start_time": null,
        "session_time": 139419127,
        "team_fastest_lap": false
    },
    {
        "ai": false,
        "car_number": "211",
        "cust_id": 676270,
        "display_name": "Cassio Medeiros",
        "flags": 0,
        "group_id": -134184,
        "helmet": {
            "color1": "ff0000",
            "color2": "000000",
            "color3": "ffffff",
            "face_type": 0,
            "helmet_type": 0,
            "pattern": 1
        },
        "incident": false,
        "lap_events": [],
        "lap_number": 57,
        "lap_time": 2395362,
        "license_level": 18,
        "name": "GROW RACING TEAM RED",
        "personal_best_lap": false,
        "session_start_time": null,
        "session_time": 141814489,
        "team_fastest_lap": false
    },
    {
        "ai": false,
        "car_number": "211",
        "cust_id": 676270,
        "display_name": "Cassio Medeiros",
        "flags": 4,
        "group_id": -134184,
        "helmet": {
            "color1": "ff0000",
            "color2": "000000",
            "color3": "ffffff",
            "face_type": 0,
            "helmet_type": 0,
            "pattern": 1
        },
        "incident": true,
        "lap_events": [
            "off track"
        ],
        "lap_number": 58,
        "lap_time": 2383103,
        "license_level": 18,
        "name": "GROW RACING TEAM RED",
        "personal_best_lap": false,
        "session_start_time": null,
        "session_time": 144197592,
        "team_fastest_lap": false
    },
    {
        "ai": false,
        "car_number": "211",
        "cust_id": 676270,
        "display_name": "Cassio Medeiros",
        "flags": 0,
        "group_id": -134184,
        "helmet": {
            "color1": "ff0000",
            "color2": "000000",
            "color3": "ffffff",
            "face_type": 0,
            "helmet_type": 0,
            "pattern": 1
        },
        "incident": false,
        "lap_events": [],
        "lap_number": 59,
        "lap_time": 2397935,
        "license_level": 18,
        "name": "GROW RACING TEAM RED",
        "personal_best_lap": false,
        "session_start_time": null,
        "session_time": 146595527,
        "team_fastest_lap": false
    },
    {
        "ai": false,
        "car_number": "211",
        "cust_id": 676270,
        "display_name": "Cassio Medeiros",
        "flags": 1,
        "group_id": -134184,
        "helmet": {
            "color1": "ff0000",
            "color2": "000000",
            "color3": "ffffff",
            "face_type": 0,
            "helmet_type": 0,
            "pattern": 1
        },
        "incident": false,
        "lap_events": [
            "invalid"
        ],
        "lap_number": 60,
        "lap_time": -1,
        "license_level": 18,
        "name": "GROW RACING TEAM RED",
        "personal_best_lap": false,
        "session_start_time": null,
        "session_time": 148993419,
        "team_fastest_lap": false
    },
    {
        "ai": false,
        "car_number": "211",
        "cust_id": 676270,
        "display_name": "Cassio Medeiros",
        "flags": 1,
        "group_id": -134184,
        "helmet": {
            "color1": "ff0000",
            "color2": "000000",
            "color3": "ffffff",
            "face_type": 0,
            "helmet_type": 0,
            "pattern": 1
        },
        "incident": false,
        "lap_events": [
            "invalid"
        ],
        "lap_number": 61,
        "lap_time": -1,
        "license_level": 18,
        "name": "GROW RACING TEAM RED",
        "personal_best_lap": false,
        "session_start_time": null,
        "session_time": 151376236,
        "team_fastest_lap": false
    },
    {
        "ai": false,
        "car_number": "211",
        "cust_id": 676270,
        "display_name": "Cassio Medeiros",
        "flags": 0,
        "group_id": -134184,
        "helmet": {
            "color1": "ff0000",
            "color2": "000000",
            "color3": "ffffff",
            "face_type": 0,
            "helmet_type": 0,
            "pattern": 1
        },
        "incident": false,
        "lap_events": [],
        "lap_number": 62,
        "lap_time": 2381944,
        "license_level": 18,
        "name": "GROW RACING TEAM RED",
        "personal_best_lap": false,
        "session_start_time": null,
        "session_time": 153758180,
        "team_fastest_lap": false
    },
    {
        "ai": false,
        "car_number": "211",
        "cust_id": 676270,
        "display_name": "Cassio Medeiros",
        "flags": 0,
        "group_id": -134184,
        "helmet": {
            "color1": "ff0000",
            "color2": "000000",
            "color3": "ffffff",
            "face_type": 0,
            "helmet_type": 0,
            "pattern": 1
        },
        "incident": false,
        "lap_events": [],
        "lap_number": 63,
        "lap_time": 2393964,
        "license_level": 18,
        "name": "GROW RACING TEAM RED",
        "personal_best_lap": false,
        "session_start_time": null,
        "session_time": 156152144,
        "team_fastest_lap": false
    },
    {
        "ai": false,
        "car_number": "211",
        "cust_id": 676270,
        "display_name": "Cassio Medeiros",
        "flags": 0,
        "group_id": -134184,
        "helmet": {
            "color1": "ff0000",
            "color2": "000000",
            "color3": "ffffff",
            "face_type": 0,
            "helmet_type": 0,
            "pattern": 1
        },
        "incident": false,
        "lap_events": [],
        "lap_number": 64,
        "lap_time": 2375136,
        "license_level": 18,
        "name": "GROW RACING TEAM RED",
        "personal_best_lap": true,
        "session_start_time": null,
        "session_time": 158527280,
        "team_fastest_lap": false
    },
    {
        "ai": false,
        "car_number": "211",
        "cust_id": 676270,
        "display_name": "Cassio Medeiros",
        "flags": 2,
        "group_id": -134184,
        "helmet": {
            "color1": "ff0000",
            "color2": "000000",
            "color3": "ffffff",
            "face_type": 0,
            "helmet_type": 0,
            "pattern": 1
        },
        "incident": false,
        "lap_events": [
            "pitted"
        ],
        "lap_number": 65,
        "lap_time": 2427083,
        "license_level": 18,
        "name": "GROW RACING TEAM RED",
        "personal_best_lap": false,
        "session_start_time": null,
        "session_time": 160954363,
        "team_fastest_lap": false
    }
]