[
    {
        "ai": false,
        "car_number": "369",
        "cust_id": 579208,
        "display_name": "Thomas Burling",
        "flags": 259,
        "group_id": -140651,
        "helmet": {
            "color1": "1f1dce",
            "color2": "000000",
            "color3": "ffffff",
            "face_type": 0,
            "helmet_type": 0,
            "pattern": 4
        },
        "incident": false,
        "lap_events": [
            "invalid",
            "pitted",
            "discontinuity"
        ],
        "lap_number": 14,
        "lap_time": -1,
        "license_level": 19,
        "name": "Chicane Online Racing Orange",
        "personal_best_lap": false,
        "session_start_time": null,
        "session_time": 37831469,
        "team_fastest_lap": false
    },
    {
        "ai": false,
        "car_number": "369",
        "cust_id": 579208,
        "display_name": "Thomas Burling",
        "flags": 0,
        "group_id": -140651,
        "helmet": {
            "color1": "1f1dce",
            "color2": "000000",
            "color3": "ffffff",
            "face_type": 0,
            "helmet_type": 0,
            "pattern": 4
        },
        "incident": false,
        "lap_events": [],
        "lap_number": 15,
        "lap_time": 2418951,
        "license_level": 19,
        "name": "Chicane Online Racing Orange",
        "personal_best_lap": false,
        "session_start_time": null,
        "session_time": 40250420,
        "team_fastest_lap": false
    },
    {
        "ai": false,
        "car_number": "369",
        "cust_id": 579208,
        "display_name": "Thomas Burling",
        "flags": 0,
        "group_id": -140651,
        "helmet": {
            "color1": "1f1dce",
            "color2": "000000",
            "color3": "ffffff",
            "face_type": 0,
            "helmet_type": 0,
            "pattern": 4
        },
        "incident": false,
        "lap_events": [],
        "lap_number": 16,
        "lap_time": 2430095,
        "license_level": 19,
        "name": "Chicane Online Racing Orange",
        "personal_best_lap": false,
        "session_start_time": null,
        "session_time": 42680515,
        "team_fastest_lap": false
    },
    {
        "ai": false,
        "car_number": "369",
        "cust_id": 579208,
        "display_name": "Thomas Burling",
        "flags": 0,
        "group_id": -140651,
        "helmet": {
            "color1": "1f1dce",
            "color2": "000000",
            "color3": "ffffff",
            "face_type": 0,
            "helmet_type": 0,
            "pattern": 4
        },
        "incident": false,
        "lap_events": [],
        "lap_number": 17,
        "lap_time": 2412962,
        "license_level": 19,
        "name": "Chicane Online Racing Orange",
        "personal_best_lap": false,
        "session_start_time": null,
        "session_time": 45093477,
        "team_fastest_lap": false
    },
    {
        "ai": false,
        "car_number": "369",
        "cust_id": 579208,
        "display_name": "Thomas Burling",
        "flags": 0,
        "group_id": -140651,
        "helmet": {
            "color1": "1f1dce",
            "color2": "000000",
            "color3": "ffffff",
            "face_type": 0,
            "helmet_type": 0,
            "pattern": 4
        },
        "incident": false,
        "lap_events": [],
        "lap_number": 18,
        "lap_time": 2413568,
        "license_level": 19,
        "name": "Chicane Online Racing Orange",
        "personal_best_lap": false,
        "session_start_time": null,
        "session_time": 47507045,
        "team_fastest_lap": false
    },
    {
        "ai": false,
        "car_number": "369",
        "cust_id": 579208,
        "display_name": "Thomas Burling",
        "flags": 0,
        "group_id": -140651,
        "helmet": {
            "color1": "1f1dce",
            "color2": "000000",
            "color3": "ffffff",
            "face_type": 0,
            "helmet_type": 0,
            "pattern": 4
        },
        "incident": false,
        "lap_events": [],
        "lap_number": 19,
        "lap_time": 2396717,
        "license_level": 19,
        "name": "Chicane Online Racing Orange",
        "personal_best_lap": false,
        "session_start_time": null,
        "session_time": 49903762,
        "team_fastest_lap": false
    },
    {
        "ai": false,
        "car_number": "369",
        "cust_id": 579208,
        "display_name": "Thomas Burling",
        "flags": 0,
        "group_id": -140651,
        "helmet": {
            "color1": "1f1dce",
            "color2": "000000",
            "color3": "ffffff",
            "face_type": 0,
            "helmet_type": 0,
            "pattern": 4
        },
        "incident": false,
        "lap_events": [],
        "lap_number": 20,
        "lap_time": 2408521,
        "license_level": 19,
        "name": "Chicane Online Racing Orange",
        "personal_best_lap": false,
        "session_start_time": null,
        "session_time": 52312283,
        "team_fastest_lap": false
    },
    {
        "ai": false,
        "car_number": "369",
        "cust_id": 579208,
        "display_name": "Thomas Burling",
        "flags": 257,
        "group_id": -140651,
        "helmet": {
            "color1": "1f1dce",
            "color2": "000000",
            "color3": "ffffff",
            "face_type": 0,
            "helmet_type": 0,
            "pattern": 4
        },
        "incident": false,
        "lap_events": [
            "invalid",
            "discontinuity"
        ],
        "lap_number": 21,
        "lap_time": -1,
        "license_level": 19,
        "name": "Chicane Online Racing Orange",
        "personal_best_lap": false,
        "session_start_time": null,
        "session_time": 54717941,
        "team_fastest_lap": false
    },
    {
        "ai": false,
        "car_number": "369",
        "cust_id": 579208,
        "display_name": "Thomas Burling",
        "flags": 0,
        "group_id": -140651,
        "helmet": {
            "color1": "1f1dce",
            "color2": "000000",
            "color3": "ffffff",
            "face_type": 0,
            "helmet_type": 0,
            "pattern": 4
        },
        "incident": false,
        "lap_events": [],
        "lap_number": 22,
        "lap_time": 2401543,
        "license_level": 19,
        "name": "Chicane Online Racing Orange",
        "personal_best_lap": false,
        "session_start_time": null,
        "session_time": 57119484,
        "team_fastest_lap": false
    },
    {
        "ai": false,
        "car_number": "369",
        "cust_id": 579208,
        "display_name": "Thomas Burling",
        "flags": 0,
        "group_id": -140651,
        "helmet": {
            "color1": "1f1dce",
            "color2": "000000",
            "color3": "ffffff",
            "face_type": 0,
            "helmet_type": 0,
            "pattern": 4
        },
        "incident": false,
        "lap_events": [],
        "lap_number": 23,
        "lap_time": 2400346,
        "license_level": 19,
        "name": "Chicane Online Racing Orange",
        "personal_best_lap": false,
        "session_start_time": null,
        "session_time": 59519830,
        "team_fastest_lap": false
    },
    {
        "ai": false,
        "car_number": "369",
        "cust_id": 579208,
        "display_name": "Thomas Burling",
        "flags": 0,
        "group_id": -140651,
        "helmet": {
            "color1": "1f1dce",
            "color2": "000000",
            "color3": "ffffff",
            "face_type": 0,
            "helmet_type": 0,
            "pattern": 4
        },
        "incident": false,
        "lap_events": [],
        "lap_number": 24,
        "lap_time": 2396377,
        "license_level": 19,
        "name": "Chicane Online Racing Orange",
        "personal_best_lap": false,
        "session_start_time": null,
        "session_time": 61916207,
        "team_fastest_lap": false
    },
    {
        "ai": false,
        "car_number": "369",
        "cust_id": 579208,
        "display_name": "Thomas Burling",
        "flags": 0,
        "group_id": -140651,
        "helmet": {
            "color1": "1f1dce",
            "color2": "000000",
            "color3": "ffffff",
            "face_type": 0,
            "helmet_type": 0,
            "pattern": 4
        },
        "incident": false,
        "lap_events": [],
        "lap_number": 25,
        "lap_time": 2396114,
        "license_level": 19,
        "name": "Chicane Online Racing Orange",
        "personal_best_lap": false,
        "session_start_time": null,
        "session_time": 64312321,
        "team_fastest_lap": false
    },
    {
        "ai": false,
        "car_number": "369",
        "cust_id": 579208,
        "display_name": "Thomas Burling",
        "flags": 2,
        "group_id": -140651,
        "helmet": {
            "color1": "1f1dce",
            "color2": "000000",
            "color3": "ffffff",
            "face_type": 0,
            "helmet_type": 0,
            "pattern": 4
        },
        "incident": false,
        "lap_events": [
            "pitted"
        ],
        "lap_number": 26,
        "lap_time": 2445254,
        "license_level": 19,
        "name": "Chicane Online Racing Orange",
        "personal_best_lap": false,
        "session_start_time": null,
        "session_time": 66757575,
        "team_fastest_lap": false
    },
    {
        "ai": false,
        "car_number": "369",
        "cust_id": 579208,
        "display_name": "Thomas Burling",
        "flags": 3,
        "group_id": -140651,
        "helmet": {
            "color1": "1f1dce",
            "color2": "000000",
            "color3": "ffffff",
            "face_type": 0,
            "helmet_type": 0,
            "pattern": 4
        },
        "incident": false,
        "lap_events": [
            "invalid",
            "pitted"
        ],
        "lap_number": 42,
        "lap_time": 3046471,
        "license_level": 19,
        "name": "Chicane Online Racing Orange",
        "personal_best_lap": false,
        "session_start_time": null,
        "session_time": 113443722,
        "team_fastest_lap": false
    },
    {
        "ai": false,
        "car_number": "369",
        "cust_id": 579208,
        "display_name": "Thomas Burling",
        "flags": 0,
        "group_id": -140651,
        "helmet": {
            "color1": "1f1dce",
            "color2": "000000",
            "color3": "ffffff",
            "face_type": 0,
            "helmet_type": 0,
            "pattern": 4
        },
        "incident": false,
        "lap_events": [],
        "lap_number": 43,
        "lap_time": 2421845,
        "license_level": 19,
        "name": "Chicane Online Racing Orange",
        "personal_best_lap": false,
        "session_start_time": null,
        "session_time": 115865567,
        "team_fastest_lap": false
    },
    {
        "ai": false,
        "car_number": "369",
        "cust_id": 579208,
        "display_name": "Thomas Burling",
        "flags": 0,
        "group_id": -140651,
        "helmet": {
            "color1": "1f1dce",
            "color2": "000000",
            "color3": "ffffff",
            "face_type": 0,
            "helmet_type": 0,
            "pattern": 4
        },
        "incident": false,
        "lap_events": [],
        "lap_number": 44,
        "lap_time": 2397465,
        "license_level": 19,
        "name": "Chicane Online Racing Orange",
        "personal_best_lap": false,
        "session_start_time": null,
        "session_time": 118263032,
        "team_fastest_lap": false
    },
    {
        "ai": false,
        "car_number": "369",
        "cust_id": 579208,
        "display_name": "Thomas Burling",
        "flags": 0,
        "group_id": -140651,
        "helmet": {
            "color1": "1f1dce",
            "color2": "000000",
            "color3": "ffffff",
            "face_type": 0,
            "helmet_type": 0,
            "pattern": 4
        },
        "incident": false,
        "lap_events": [],
        "lap_number": 45,
        "lap_time": 2415500,
        "license_level": 19,
        "name": "Chicane Online Racing Orange",
        "personal_best_lap": false,
        "session_start_time": null,
        "session_time": 120678532,
        "team_fastest_lap": false
    },
    {
        "ai": false,
        "car_number": "369",
        "cust_id": 579208,
        "display_name": "Thomas Burling",
        "flags": 0,
        "group_id": -140651,
        "helmet": {
            "color1": "1f1dce",
            "color2": "000000",
            "color3": "ffffff",
            "face_type": 0,
            "helmet_type": 0,
            "pattern": 4
        },
        "incident": false,
        "lap_events": [],
        "lap_number": 46,
        "lap_time": 2412844,
        "license_level": 19,
        "name": "Chicane Online Racing Orange",
        "personal_best_lap": false,
        "session_start_time": null,
        "session_time": 123091376,
        "team_fastest_lap": false
    },
    {
        "ai": false,
        "car_number": "369",
        "cust_id": 579208,
        "display_name": "Thomas Burling",
        "flags": 0,
        "group_id": -140651,
        "helmet": {
            "color1": "1f1dce",
            "color2": "000000",
            "color3": "ffffff",
            "face_type": 0,
            "helmet_type": 0,
            "pattern": 4
        },
        "incident": false,
        "lap_events": [],
        "lap_number": 47,
        "lap_time": 2401921,
        "license_level": 19,
        "name": "Chicane Online Racing Orange",
        "personal_best_lap": false,
        "session_start_time": null,
        "session_time": 125493297,
        "team_fastest_lap": false
    },
    {
        "ai": false,
        "car_number": "369",
        "cust_id": 579208,
        "display_name": "Thomas Burling",
        "flags": 0,
        "group_id": -140651,
        "helmet": {
            "color1": "1f1dce",
            "color2": "000000",
            "color3": "ffffff",
            "face_type": 0,
            "helmet_type": 0,
            "pattern": 4
        },
        "incident": false,
        "lap_events": [],
        "lap_number": 48,
        "lap_time": 2400212,
        "license_level": 19,
        "name": "Chicane Online Racing Orange",
        "personal_best_lap": false,
        "session_start_time": null,
        "session_time": 127893509,
        "team_fastest_lap": false
    },
    {
        "ai": false,
        "car_number": "369",
        "cust_id": 579208,
        "display_name": "Thomas Burling",
        "flags": 0,
        "group_id": -140651,
        "helmet": {
            "color1": "1f1dce",
            "color2": "000000",
            "color3": "ffffff",
            "face_type": 0,
            "helmet_type": 0,
            "pattern": 4
        },
        "incident": false,
        "lap_events": [],
        "lap_number": 49,
        "lap_time": 2393558,
        "license_level": 19,
        "name": "Chicane Online Racing Orange",
        "personal_best_lap": false,
        "session_start_time": null,
        "session_time": 130287067,
        "team_fastest_lap": false
    },
    {
        "ai": false,
        "car_number": "369",
        "cust_id": 579208,
        "display_name": "Thomas Burling",
        "flags": 0,
        "group_id": -140651,
        "helmet": {
            "color1": "1f1dce",
            "color2": "000000",
            "color3": "ffffff",
            "face_type": 0,
            "helmet_type": 0,
            "pattern": 4
        },
        "incident": false,
        "lap_events": [],
        "lap_number": 50,
        "lap_time": 2408658,
        "license_level": 19,
        "name": "Chicane Online Racing Orange",
        "personal_best_lap": false,
        "session_start_time": null,
        "session_time": 132695725,
        "team_fastest_lap": false
    },
    {
        "ai": false,
        "car_number": "369",
        "cust_id": 579208,
        "display_name": "Thomas Burling",
        "flags": 0,
        "group_id": -140651,
        "helmet": {
            "color1": "1f1dce",
            "color2": "000000",
            "color3": "ffffff",
            "face_type": 0,
            "helmet_type": 0,
            "pattern": 4
        },
        "incident": false,
        "lap_events": [],
        "lap_number": 51,
        "lap_time": 2398641,
        "license_level": 19,
        "name": "Chicane Online Racing Orange",
        "personal_best_lap": false,
        "session_start_time": null,
        "session_time": 135094366,
        "team_fastest_lap": false
    },
    {
        "ai": false,
        "car_number": "369",
        "cust_id": 579208,
        "display_name": "Thomas Burling",
        "flags": 0,
        "group_id": -140651,
        "helmet": {
            "color1": "1f1dce",
            "color2": "000000",
            "color3": "ffffff",
            "face_type": 0,
            "helmet_type": 0,
            "pattern": 4
        },
        "incident": false,
        "lap_events": [],
        "lap_number": 52,
        "lap_time": 2394815,
        "license_level": 19,
        "name": "Chicane Online Racing Orange",
        "personal_best_lap": false,
        "session_start_time": null,
        "session_time": 137489181,
        "team_fastest_lap": false
    },
    {
        "ai": false,
        "car_number": "369",
        "cust_id": 579208,
        "display_name": "Thomas Burling",
        "flags": 0,
        "group_id": -140651,
        "helmet": {
            "color1": "1f1dce",
            "color2": "000000",
            "color3": "ffffff",
            "face_type": 0,
            "helmet_type": 0,
            "pattern": 4
        },
        "incident": false,
        "lap_events": [],
        "lap_number": 53,
        "lap_time": 2401101,
        "license_level": 19,
        "name": "Chicane Online Racing Orange",
        "personal_best_lap": false,
        "session_start_time": null,
        "session_time": 139890282,
        "team_fastest_lap": false
    },
    {
        "ai": false,
        "car_number": "369",
        "cust_id": 579208,
        "display_name": "Thomas Burling",
        "flags": 2,
        "group_id": -140651,
        "helmet": {
            "color1": "1f1dce",
            "color2": "000000",
            "color3": "ffffff",
            "face_type": 0,
            "helmet_type": 0,
            "pattern": 4
        },
        "incident": false,
        "lap_events": [
            "pitted"
        ],
        "lap_number": 54,
        "lap_time": 2446277,
        "license_level": 19,
        "name": "Chicane Online Racing Orange",
        "personal_best_lap": false,
        "session_start_time": null,
        "session_time": 142336559,
        "team_fastest_lap": false
    },
    {
        "ai": false,
        "car_number": "369",
        "cust_id": 579208,
        "display_name": "Thomas Burling",
        "flags": 6,
        "group_id": -140651,
        "helmet": {
            "color1": "1f1dce",
            "color2": "000000",
            "color3": "ffffff",
            "face_type": 0,
            "helmet_type": 0,
            "pattern": 4
        },
        "incident": true,
        "lap_events": [
            "pitted",
            "off track"
        ],
        "lap_number": 55,
        "lap_time": 3037072,
        "license_level": 19,
        "name": "Chicane Online Racing Orange",
        "personal_best_lap": false,
        "session_start_time": null,
        "session_time": 145373631,
        "team_fastest_lap": false
    },
    {
        "ai": false,
        "car_number": "369",
        "cust_id": 579208,
        "display_name": "Thomas Burling",
        "flags": 0,
        "group_id": -140651,
        "helmet": {
            "color1": "1f1dce",
            "color2": "000000",
            "color3": "ffffff",
            "face_type": 0,
            "helmet_type": 0,
            "pattern": 4
        },
        "incident": false,
        "lap_events": [],
        "lap_number": 56,
        "lap_time": 2414441,
        "license_level": 19,
        "name": "Chicane Online Racing Orange",
        "personal_best_lap": false,
        "session_start_time": null,
        "session_time": 147788072,
        "team_fastest_lap": false
    },
    {
        "ai": false,
        "car_number": "369",
        "cust_id": 579208,
        "display_name": "Thomas Burling",
        "flags": 4,
        "group_id": -140651,
        "helmet": {
            "color1": "1f1dce",
            "color2": "000000",
            "color3": "ffffff",
            "face_type": 0,
            "helmet_type": 0,
            "pattern": 4
        },
        "incident": true,
        "lap_events": [
            "off track"
        ],
        "lap_number": 57,
        "lap_time": 2405417,
        "license_level": 19,
        "name": "Chicane Online Racing Orange",
        "personal_best_lap": false,
        "session_start_time": null,
        "session_time": 150193489,
        "team_fastest_lap": false
    },
    {
        "ai": false,
        "car_number": "369",
        "cust_id": 579208,
        "display_name": "Thomas Burling",
        "flags": 0,
        "group_id": -140651,
        "helmet": {
            "color1": "1f1dce",
            "color2": "000000",
            "color3": "ffffff",
            "face_type": 0,
            "helmet_type": 0,
            "pattern": 4
        },
        "incident": false,
        "lap_events": [],
        "lap_number": 58,
        "lap_time": 2405783,
        "license_level": 19,
        "name": "Chicane Online Racing Orange",
        "personal_best_lap": false,
        "session_start_time": null,
        "session_time": 152599272,
        "team_fastest_lap": false
    },
    {
        "ai": false,
        "car_number": "369",
        "cust_id": 579208,
        "display_name": "Thomas Burling",
        "flags": 0,
        "group_id": -140651,
        "helmet": {
            "color1": "1f1dce",
            "color2": "000000",
            "color3": "ffffff",
            "face_type": 0,
            "helmet_type": 0,
            "pattern": 4
        },
        "incident": false,
        "lap_events": [],
        "lap_number": 59,
        "lap_time": 2398838,
        "license_level": 19,
        "name": "Chicane Online Racing Orange",
        "personal_best_lap": false,
        "session_start_time": null,
        "session_time": 154998110,
        "team_fastest_lap": false
    },
    {
        "ai": false,
        "car_number": "369",
        "cust_id": 579208,
        "display_name": "Thomas Burling",
        "flags": 0,
        "group_id": -140651,
        "helmet": {
            "color1": "1f1dce",
            "color2": "000000",
            "color3": "ffffff",
            "face_type": 0,
            "helmet_type": 0,
            "pattern": 4
        },
        "incident": false,
        "lap_events": [],
        "lap_number": 60,
        "lap_time": 2400916,
        "license_level": 19,
        "name": "Chicane Online Racing Orange",
        "personal_best_lap": false,
        "session_start_time": null,
        "session_time": 157399026,
        "team_fastest_lap": false
    },
    {
        "ai": false,
        "car_number": "369",
        "cust_id": 579208,
        "display_name": "Thomas Burling",
        "flags": 0,
        "group_id": -140651,
        "helmet": {
            "color1": "1f1dce",
            "color2": "000000",
            "color3": "ffffff",
            "face_type": 0,
            "helmet_type": 0,
            "pattern": 4
        },
        "incident": false,
        "lap_events": [],
        "lap_number": 61,
        "lap_time": 2390861,
        "license_level": 19,
        "name": "Chicane Online Racing Orange",
        "personal_best_lap": false,
        "session_start_time": null,
        "session_time": 159789887,
        "team_fastest_lap": false
    },
    {
        "ai": false,
        "car_number": "369",
        "cust_id": 579208,
        "display_name": "Thomas Burling",
        "flags": 0,
        "group_id": -140651,
        "helmet": {
            "color1": "1f1dce",
            "color2": "000000",
            "color3": "ffffff",
            "face_type": 0,
            "helmet_type": 0,
            "pattern": 4
        },
        "incident": false,
        "lap_events": [],
        "lap_number": 62,
        "lap_time": 2400532,
        "license_level": 19,
        "name": "Chicane Online Racing Orange",
        "personal_best_lap": false,
        "session_start_time": null,
        "session_time": 162190419,
        "team_fastest_lap": false
    },
    {
        "ai": false,
        "car_number": "369",
        "cust_id": 579208,
        "display_name": "Thomas Burling",
        "flags": 0,
        "group_id": -140651,
        "helmet": {
            "color1": "1f1dce",
            "color2": "000000",
            "color3": "ffffff",
            "face_type": 0,
            "helmet_type": 0,
            "pattern": 4
        },
        "incident": false,
        "lap_events": [],
        "lap_number": 63,
        "lap_time": 2389271,
        "license_level": 19,
        "name": "Chicane Online Racing Orange",
        "personal_best_lap": false,
        "session_start_time": null,
        "session_time": 164579690,
        "team_fastest_lap": false
    },
    {
        "ai": false,
        "car_number": "369",
        "cust_id": 579208,
        "display_name": "Thomas Burling",
        "flags": 0,
        "group_id": -140651,
        "helmet": {
            "color1": "1f1dce",
            "color2": "000000",
            "color3": "ffffff",
            "face_type": 0,
            "helmet_type": 0,
            "pattern": 4
        },
        "incident": false,
        "lap_events": [],
        "lap_number": 64,
        "lap_time": 2393826,
        "license_level": 19,
        "name": "Chicane Online Racing Orange",
        "personal_best_lap": false,
        "session_start_time": null,
        "session_time": 166973516,
        "team_fastest_lap": false
    },
    {
        "ai": false,
        "car_number": "369",
        "cust_id": 579208,
        "display_name": "Thomas Burling",
        "flags": 0,
        "group_id": -140651,
        "helmet": {
            "color1": "1f1dce",
            "color2": "000000",
            "color3": "ffffff",
            "face_type": 0,
            "helmet_type": 0,
            "pattern": 4
        },
        "incident": false,
        "lap_events": [],
        "lap_number": 65,
        "lap_time": 2390273,
        "license_level": 19,
        "name": "Chicane Online Racing Orange",
        "personal_best_lap": false,
        "session_start_time": null,
        "session_time": 169363789,
        "team_fastest_lap": false
    },
    {
        "ai": false,
        "car_number": "369",
        "cust_id": 579208,
        "display_name": "Thomas Burling",
        "flags": 0,
        "group_id": -140651,
        "helmet": {
            "color1": "1f1dce",
            "color2": "000000",
            "color3": "ffffff",
            "face_type": 0,
            "helmet_type": 0,
            "pattern": 4
        },
        "incident": false,
        "lap_events": [],
        "lap_number": 66,
        "lap_time": 2375804,
        "license_level": 19,
        "name": "Chicane Online Racing Orange",
        "personal_best_lap": true,
        "session_start_time": null,
        "session_time": 171739593,
        "team_fastest_lap": false
    },
    {
        "ai": false,
        "car_number": "369",
        "cust_id": 579208,
        "display_name": "Thomas Burling",
        "flags": 258,
        "group_id": -140651,
        "helmet": {
            "color1": "1f1dce",
            "color2": "000000",
            "color3": "ffffff",
            "face_type": 0,
            "helmet_type": 0,
            "pattern": 4
        },
        "incident": false,
        "lap_events": [
            "pitted",
            "discontinuity"
        ],
        "lap_number": 67,
        "lap_time": -1,
        "license_level": 19,
        "name": "Chicane Online Racing Orange",
        "personal_best_lap": false,
        "session_start_time": null,
        "session_time": 174166429,
        "team_fastest_lap": false
    }
]